[
{
  "id": 11,
  "name": "Abrazo/Mitchard Birthmother Scholarship Fund",
  "provider": "Mitchard Birthmother Scholarship Fund",
  "amount": "1000",

  "deadline": "February 24",
  "description": "Requirements: Accounting, Business, Transportation, and Management",
  "requirements": ["Available for all areas of study"]
},

{
  "id": 12,
  "name": "MLK Foundation Scholarship",
  "provider": "MLK Foundation Scholars",
  "amount": "5000",

  "deadline": "February 24",
  "description": "Requirements: Accounting, Business, Transportation, and Management",
  "requirements": ["Available for all areas of study"]
}
]